omnicloud/airport/terminals/_dict/_gcp/__init__.py
omnicloud/airport/terminals/_dict/_gcp/gate.py
omnicloud/airport/tools/gcp/__init__.py
omnicloud/airport/tools/gcp/storage.py
omnicloud_airport_gcp-0.0.1.dist-info/LICENSE
omnicloud_airport_gcp-0.0.1.dist-info/METADATA
omnicloud_airport_gcp-0.0.1.dist-info/WHEEL
omnicloud_airport_gcp-0.0.1.dist-info/RECORD
