Metadata-Version: 2.1
Name: omnicloud-airport-gcp
Version: 0.0.1
Summary: Set of Gates to Google Cloud Platform for Omnicloud Airport
Home-page: https://omnicloud.world/airport
Keywords: omnicloud,supercloud,multicloud,cloud computing,migration,gcp,Google
Author: Iurii Tarasenko
Author-email: iurii@omnicloud.world
Requires-Python: >=3.10,<4.0
Classifier: Intended Audience :: Developers
Classifier: Intended Audience :: Information Technology
Classifier: License :: OSI Approved :: MIT License
Classifier: Programming Language :: Python :: 3
Classifier: Programming Language :: Python :: 3.10
Classifier: Programming Language :: Python :: 3.11
Classifier: Programming Language :: Python :: 3.10
Classifier: Topic :: Software Development :: Libraries :: Python Modules
Requires-Dist: google-cloud-storage (>=2.7.0,<3.0.0)
Requires-Dist: omnicloud-airport (>=0.0.1,<0.0.2)
Project-URL: Documentation, https://docs.omnicloud.world/py-airport
Project-URL: Repository, https://github.com/omnicloudworld/py.airport.gcp
